govee_api2/__init__.py
govee_api2/api.py
govee_api2/device.py
govee_api2/device_factory.py
govee_api2/cert/AmazonRootCA1.pem
govee_api2/cert/testiot.cert.pem
govee_api2/cert/testiot.cert.pkey
govee_api2-1.3.0.dist-info/AUTHORS.rst
govee_api2-1.3.0.dist-info/LICENSE.rst
govee_api2-1.3.0.dist-info/METADATA
govee_api2-1.3.0.dist-info/WHEEL
govee_api2-1.3.0.dist-info/top_level.txt
govee_api2-1.3.0.dist-info/RECORD
