Metadata-Version: 2.1
Name: govee-api2
Version: 1.3.0
Summary: Simple and minimal Govee Home API client
Home-page: https://github.com/filipealvesdef/govee_api/tree/filipealves-setup-fixes
Author: Thomas Reiser
Author-email: reiser.thomas@gmail.com
License: Apache Software License
Keywords: govee_api2
Platform: UNKNOWN
Classifier: Development Status :: 5 - Production/Stable
Classifier: Intended Audience :: Developers
Classifier: License :: OSI Approved :: Apache Software License
Classifier: Natural Language :: English
Classifier: Natural Language :: German
Classifier: Programming Language :: Python :: 3
Classifier: Programming Language :: Python :: 3.5
Classifier: Programming Language :: Python :: 3.6
Classifier: Programming Language :: Python :: 3.7
Classifier: Programming Language :: Python :: 3.8
Classifier: Operating System :: OS Independent
Classifier: Topic :: Home Automation
Requires-Python: >=3.5
License-File: LICENSE.rst
License-File: AUTHORS.rst
Requires-Dist: Click (>=7.0)
Requires-Dist: AWSIoTPythonSDK
Requires-Dist: colour
Requires-Dist: requests
Requires-Dist: PyJWT (==1.7.1)
